corus/__init__.py
corus/io.py
corus/path.py
corus/readme.py
corus/record.py
corus/zip.py
corus/sources/__init__.py
corus/sources/bsnlp.py
corus/sources/buriy.py
corus/sources/corpora.py
corus/sources/factru.py
corus/sources/gareev.py
corus/sources/gramru.py
corus/sources/lenta.py
corus/sources/librusec.py
corus/sources/meta.py
corus/sources/mokoron.py
corus/sources/morphoru.py
corus/sources/ne5.py
corus/sources/ods.py
corus/sources/omnia.py
corus/sources/persons.py
corus/sources/ria.py
corus/sources/rudrec.py
corus/sources/russe.py
corus/sources/simlex.py
corus/sources/toloka.py
corus/sources/ud.py
corus/sources/wiki.py
corus/sources/wikiner.py
corus/sources/taiga/__init__.py
corus/sources/taiga/arzamas.py
corus/sources/taiga/common.py
corus/sources/taiga/fontanka.py
corus/sources/taiga/interfax.py
corus/sources/taiga/kp.py
corus/sources/taiga/lenta.py
corus/sources/taiga/magazines.py
corus/sources/taiga/nplus1.py
corus/sources/taiga/proza.py
corus/sources/taiga/social.py
corus/sources/taiga/subtitles.py
corus/third/WikiExtractor.py
corus/third/__init__.py
corus-0.10.0.dist-info/LICENSE
corus-0.10.0.dist-info/METADATA
corus-0.10.0.dist-info/WHEEL
corus-0.10.0.dist-info/top_level.txt
corus-0.10.0.dist-info/RECORD
