Metadata-Version: 2.1
Name: corus
Version: 0.10.0
Summary: Links to russian corpora, functions for loading and parsing
Home-page: https://github.com/natasha/corus
Author: Alexander Kukushkin
Author-email: alex@alexkuk.ru
License: MIT
Keywords: corpora,russian,nlp,datasets
Classifier: License :: OSI Approved :: MIT License
Classifier: Programming Language :: Python :: 3
License-File: LICENSE
